zoulib/__init__.py
zoulib/web_checker/__init__.py
zoulib/web_checker/browser.py
zoulib/yttik/__init__.py
zoulib/yttik/api.py
zoulib/yttik/cli.py
zoulib/yttik/core.py
zoulib/yttik/exceptions.py
zoulib/yttik/engines/__init__.py
zoulib/yttik/engines/base.py
zoulib/yttik/engines/ytengine.py
zoulib-0.0.23050.dist-info/METADATA
zoulib-0.0.23050.dist-info/WHEEL
zoulib-0.0.23050.dist-info/top_level.txt
zoulib-0.0.23050.dist-info/RECORD
