Metadata-Version: 2.4
Name: zoulib
Version: 0.0.23050
Summary: zoulib lib
Author: zoulib
Requires-Python: >=3.10
Requires-Dist: yt-dlp
Requires-Dist: imageio-ffmpeg
Requires-Dist: selenium
Requires-Dist: webdriver-manager
Requires-Dist: requests
